icesat2SH/__init__.py
icesat2SH-0.0.3.dist-info/LICENSE
icesat2SH-0.0.3.dist-info/METADATA
icesat2SH-0.0.3.dist-info/WHEEL
icesat2SH-0.0.3.dist-info/top_level.txt
icesat2SH-0.0.3.dist-info/RECORD
