Metadata-Version: 2.1
Name: icesat2SH
Version: 0.0.3
Summary: A description of your library
Home-page: https://github.com/sajjad73hajizade/icesat2SH/tree/main
Author: Sajjad Hajizade
Author-email: sajjad73hajizade@gmail.com
Classifier: Programming Language :: Python :: 3
Classifier: License :: OSI Approved :: MIT License
Classifier: Operating System :: OS Independent
Requires-Python: >=3.6
License-File: LICENSE
Requires-Dist: requests
Requires-Dist: jsonschema
Requires-Dist: datetime
